perform_topsis/102103766.py
Topsis_Neelakshi_Gupta_102103766-1.0.0.dist-info/LICENSE
Topsis_Neelakshi_Gupta_102103766-1.0.0.dist-info/METADATA
Topsis_Neelakshi_Gupta_102103766-1.0.0.dist-info/WHEEL
Topsis_Neelakshi_Gupta_102103766-1.0.0.dist-info/entry_points.txt
Topsis_Neelakshi_Gupta_102103766-1.0.0.dist-info/top_level.txt
Topsis_Neelakshi_Gupta_102103766-1.0.0.dist-info/RECORD
