Metadata-Version: 2.1
Name: Topsis-Neelakshi_Gupta-102103766
Version: 1.0.0
Summary: Performs TOPSIS
Home-page: https://github.com/neelakshidob/Topsis-implementation.git
Author: Neelakshi Gupta
Author-email: ngupta_be21@thapar.edu
License: MIT
Classifier: License :: OSI Approved :: MIT License
Classifier: Programming Language :: Python :: 3.6
Classifier: Programming Language :: Python :: 3.7
Classifier: Programming Language :: Python :: 3.8
License-File: LICENSE
